frequenz/client/assets/__init__.py
frequenz/client/assets/_client.py
frequenz/client/assets/_delivery_area.py
frequenz/client/assets/_delivery_area_proto.py
frequenz/client/assets/_lifetime.py
frequenz/client/assets/_lifetime_proto.py
frequenz/client/assets/_location.py
frequenz/client/assets/_location_proto.py
frequenz/client/assets/_microgrid.py
frequenz/client/assets/_microgrid_json.py
frequenz/client/assets/_microgrid_proto.py
frequenz/client/assets/_utils.py
frequenz/client/assets/conftest.py
frequenz/client/assets/exceptions.py
frequenz/client/assets/py.typed
frequenz/client/assets/cli/__init__.py
frequenz/client/assets/cli/__main__.py
frequenz/client/assets/cli/_utils.py
frequenz/client/assets/electrical_component/__init__.py
frequenz/client/assets/electrical_component/_battery.py
frequenz/client/assets/electrical_component/_breaker.py
frequenz/client/assets/electrical_component/_capacitor_bank.py
frequenz/client/assets/electrical_component/_category.py
frequenz/client/assets/electrical_component/_chp.py
frequenz/client/assets/electrical_component/_converter.py
frequenz/client/assets/electrical_component/_crypto_miner.py
frequenz/client/assets/electrical_component/_electrical_component.py
frequenz/client/assets/electrical_component/_electrical_component_json.py
frequenz/client/assets/electrical_component/_electrical_component_proto.py
frequenz/client/assets/electrical_component/_electrolyzer.py
frequenz/client/assets/electrical_component/_ev_charger.py
frequenz/client/assets/electrical_component/_grid_connection_point.py
frequenz/client/assets/electrical_component/_hvac.py
frequenz/client/assets/electrical_component/_inverter.py
frequenz/client/assets/electrical_component/_meter.py
frequenz/client/assets/electrical_component/_plc.py
frequenz/client/assets/electrical_component/_power_transformer.py
frequenz/client/assets/electrical_component/_precharger.py
frequenz/client/assets/electrical_component/_problematic.py
frequenz_client_assets-0.0.2.dist-info/licenses/LICENSE
frequenz_client_assets-0.0.2.dist-info/METADATA
frequenz_client_assets-0.0.2.dist-info/WHEEL
frequenz_client_assets-0.0.2.dist-info/entry_points.txt
frequenz_client_assets-0.0.2.dist-info/top_level.txt
frequenz_client_assets-0.0.2.dist-info/RECORD
