Metadata-Version: 2.4
Name: frequenz-client-assets
Version: 0.0.2
Summary: Assets API client for Python
Author-email: Frequenz Energy-as-a-Service GmbH <floss@frequenz.com>
License: MIT
Project-URL: Documentation, https://frequenz-floss.github.io/frequenz-client-assets-python/
Project-URL: Changelog, https://github.com/frequenz-floss/frequenz-client-assets-python/releases
Project-URL: Issues, https://github.com/frequenz-floss/frequenz-client-assets-python/issues
Project-URL: Repository, https://github.com/frequenz-floss/frequenz-client-assets-python
Project-URL: Support, https://github.com/frequenz-floss/frequenz-client-assets-python/discussions/categories/support
Keywords: frequenz,python,lib,library,frequenz-client-assets,client-assets,client,assets,api
Classifier: Development Status :: 3 - Alpha
Classifier: Intended Audience :: Developers
Classifier: License :: OSI Approved :: MIT License
Classifier: Programming Language :: Python :: 3
Classifier: Programming Language :: Python :: 3 :: Only
Classifier: Topic :: Software Development :: Libraries
Classifier: Typing :: Typed
Requires-Python: <4,>=3.11
License-File: LICENSE
Requires-Dist: typing-extensions<5,>=4.13.0
Requires-Dist: frequenz-api-assets<0.2.0,>=0.1.0
Requires-Dist: frequenz-api-common<1,>=0.8.0
Requires-Dist: frequenz-client-base<0.12.0,>=0.11.0
Requires-Dist: frequenz-client-common<0.4.0,>=0.3.6
Requires-Dist: grpcio<2,>=1.73.1
Provides-Extra: cli
Requires-Dist: asyncclick==8.3.0.4; extra == "cli"
Provides-Extra: dev-flake8
Requires-Dist: flake8==7.3.0; extra == "dev-flake8"
Requires-Dist: flake8-docstrings==1.7.0; extra == "dev-flake8"
Requires-Dist: flake8-pyproject==1.2.3; extra == "dev-flake8"
Requires-Dist: pydoclint==0.6.10; extra == "dev-flake8"
Requires-Dist: pydocstyle==6.3.0; extra == "dev-flake8"
Provides-Extra: dev-formatting
Requires-Dist: black==25.9.0; extra == "dev-formatting"
Requires-Dist: isort==6.1.0; extra == "dev-formatting"
Provides-Extra: dev-mkdocs
Requires-Dist: Markdown==3.9; extra == "dev-mkdocs"
Requires-Dist: black==25.9.0; extra == "dev-mkdocs"
Requires-Dist: mike==2.1.3; extra == "dev-mkdocs"
Requires-Dist: mkdocs-gen-files==0.5.0; extra == "dev-mkdocs"
Requires-Dist: mkdocs-literate-nav==0.6.2; extra == "dev-mkdocs"
Requires-Dist: mkdocs-macros-plugin==1.4.0; extra == "dev-mkdocs"
Requires-Dist: mkdocs-material==9.6.17; extra == "dev-mkdocs"
Requires-Dist: mkdocstrings[python]==0.30.0; extra == "dev-mkdocs"
Requires-Dist: mkdocstrings-python==1.18.2; extra == "dev-mkdocs"
Requires-Dist: frequenz-repo-config[lib]==0.13.5; extra == "dev-mkdocs"
Provides-Extra: dev-mypy
Requires-Dist: mypy==1.18.2; extra == "dev-mypy"
Requires-Dist: grpc-stubs==1.53.0.6; extra == "dev-mypy"
Requires-Dist: types-Markdown==3.9.0.20250906; extra == "dev-mypy"
Requires-Dist: types-protobuf==6.32.1.20250918; extra == "dev-mypy"
Requires-Dist: frequenz-client-assets[cli,dev-mkdocs,dev-noxfile,dev-pytest]; extra == "dev-mypy"
Provides-Extra: dev-noxfile
Requires-Dist: nox==2025.5.1; extra == "dev-noxfile"
Requires-Dist: frequenz-repo-config[lib]==0.13.5; extra == "dev-noxfile"
Provides-Extra: dev-pylint
Requires-Dist: frequenz-client-assets[cli,dev-mkdocs,dev-noxfile,dev-pytest]; extra == "dev-pylint"
Provides-Extra: dev-pytest
Requires-Dist: pytest==8.4.1; extra == "dev-pytest"
Requires-Dist: pylint==3.3.8; extra == "dev-pytest"
Requires-Dist: frequenz-repo-config[extra-lint-examples]==0.13.5; extra == "dev-pytest"
Requires-Dist: pytest-mock==3.15.1; extra == "dev-pytest"
Requires-Dist: pytest-asyncio==1.1.0; extra == "dev-pytest"
Requires-Dist: async-solipsism==0.8; extra == "dev-pytest"
Provides-Extra: dev
Requires-Dist: frequenz-client-assets[dev-flake8,dev-formatting,dev-mkdocs,dev-mypy,dev-noxfile,dev-pylint,dev-pytest]; extra == "dev"
Dynamic: license-file
